odoo/addons/shopinvader_sale_cart_no_onchange_helper/README.rst
odoo/addons/shopinvader_sale_cart_no_onchange_helper/__init__.py
odoo/addons/shopinvader_sale_cart_no_onchange_helper/__manifest__.py
odoo/addons/shopinvader_sale_cart_no_onchange_helper/i18n/shopinvader_sale_cart_no_onchange_helper.pot
odoo/addons/shopinvader_sale_cart_no_onchange_helper/models/__init__.py
odoo/addons/shopinvader_sale_cart_no_onchange_helper/models/sale_order_line.py
odoo/addons/shopinvader_sale_cart_no_onchange_helper/readme/CONTRIBUTORS.rst
odoo/addons/shopinvader_sale_cart_no_onchange_helper/readme/DESCRIPTION.rst
odoo/addons/shopinvader_sale_cart_no_onchange_helper/static/description/index.html
odoo_addon_shopinvader_sale_cart_no_onchange_helper-16.0.1.0.1.dist-info/METADATA
odoo_addon_shopinvader_sale_cart_no_onchange_helper-16.0.1.0.1.dist-info/WHEEL
odoo_addon_shopinvader_sale_cart_no_onchange_helper-16.0.1.0.1.dist-info/top_level.txt
odoo_addon_shopinvader_sale_cart_no_onchange_helper-16.0.1.0.1.dist-info/RECORD
