Metadata-Version: 2.1
Name: odoo-addon-shopinvader_sale_cart_no_onchange_helper
Version: 16.0.1.0.1
Summary: Disables the use of onchange_helper in shopinvader_sale_cart
Home-page: https://github.com/shopinvader/odoo-shopinvader
Author: CamptoCamp, Odoo Community Association (OCA)
Author-email: support@odoo-community.org
License: AGPL-3
Classifier: Programming Language :: Python
Classifier: Framework :: Odoo
Classifier: Framework :: Odoo :: 16.0
Classifier: License :: OSI Approved :: GNU Affero General Public License v3
Requires-Python: >=3.10
Requires-Dist: odoo-addon-shopinvader-sale-cart<16.1dev,>=16.0dev
Requires-Dist: odoo<16.1dev,>=16.0a
